kyotsu-0.0.1.dist-info/METADATA
kyotsu-0.0.1.dist-info/WHEEL
kyotsu-0.0.1.dist-info/licenses/LICENSE.txt
kyotsu/__init__.py
kyotsu/config/__init__.py
kyotsu/config/base.py
kyotsu/config/databases/__init__.py
kyotsu/config/databases/_types.py
kyotsu/config/databases/models.py
kyotsu/config/misc/__init__.py
kyotsu/config/misc/celery.py
kyotsu/config/services.py
kyotsu/db/__init__.py
kyotsu/db/sqlalchemy/__init__.py
kyotsu/db/sqlalchemy/base.py
kyotsu/db/sqlalchemy/mixins.py
kyotsu/db/sqlalchemy/session_maker.py
kyotsu/fastapi/__init__.py
kyotsu/fastapi/middleware.py
kyotsu/fastapi/models.py
kyotsu/fastapi/openapi/__init__.py
kyotsu/fastapi/openapi/metadata.py
kyotsu/fastapi/openapi/routes.py
kyotsu/logging/ToDo.md
kyotsu/logging/__init__.py
kyotsu/logging/config.py
kyotsu/logging/error_codes/__init__.py
kyotsu/logging/error_codes/dataclasses.py
kyotsu/logging/error_codes/definitions/__init__.py
kyotsu/logging/error_codes/definitions/_constants.py
kyotsu/logging/error_codes/definitions/_keeper.py
kyotsu/logging/error_codes/definitions/kyotsu.py
kyotsu/logging/error_codes/definitions/uncategorized.py
kyotsu/logging/error_codes/processors.py
kyotsu/logging/exceptions.py
kyotsu/logging/groups/__init__.py
kyotsu/logging/groups/constants.py
kyotsu/logging/groups/processors.py
kyotsu/logging/opensearch/__init__.py
kyotsu/logging/opensearch/processors.py
kyotsu/logging/telemetry/__init__.py
kyotsu/logging/telemetry/clients.py
kyotsu/logging/telemetry/constants.py
kyotsu/logging/telemetry/contextvars.py
kyotsu/logging/telemetry/processors.py
kyotsu/logging/telemetry/utils.py
kyotsu/logging/utils.py
kyotsu/py.typed
kyotsu/utils/__init__.py
kyotsu/utils/contextmanagers.py
kyotsu/utils/types.py
kyotsu-0.0.1.dist-info/RECORD
